sqs_poller/__init__.py
sqs_poller/sqs_poller.py
sqs_poller-0.0.9.dist-info/LICENSE
sqs_poller-0.0.9.dist-info/METADATA
sqs_poller-0.0.9.dist-info/WHEEL
sqs_poller-0.0.9.dist-info/top_level.txt
sqs_poller-0.0.9.dist-info/RECORD
