Metadata-Version: 2.1
Name: sqs-poller
Version: 0.0.9
Summary: A wrapper class around boto3's SQS resource.
Home-page: https://github.com/nordhealth/sqs-poller
Author: Ville Lindroos
Author-email: ville.lindroos@nordhealth.com
Project-URL: Nordhealth, https://nordhealth.com
Classifier: Programming Language :: Python :: 3
Classifier: Programming Language :: Python :: 2.7
Classifier: Operating System :: OS Independent
Classifier: Development Status :: 3 - Alpha
Classifier: License :: OSI Approved :: MIT License
Requires-Python: >=2.7
License-File: LICENSE
Requires-Dist: boto3 >=1.17.112
Provides-Extra: tests
Requires-Dist: pytest <7 ; extra == 'tests'
Requires-Dist: moto[sqs] <3 ; extra == 'tests'
